{"assets":{"9076D6E0EFACFF14A26F2273D9135919":{"type":"texture","index":1,"url":{"native":"assets\/B14D9022-3280-420C-8D07-0B6BF708DBB2.pdf"},"width":1920,"height":1080},"C22916240A8F8EF9D314E0ED6FA88D7B":{"type":"texture","index":0,"url":{"native":"assets\/B14D9022-3280-420C-8D07-0B6BF708DBB2.pdf"},"width":1920,"height":1080}},"events":[{"effects":[{"beginTime":0,"baseLayer":{"animations":[],"initialState":{"affineTransform":[1,0,0,1,0,0],"masksToBounds":false,"rotation":0,"scale":1,"position":{"pointX":960,"pointY":540},"width":1920,"sublayerTransform":[1,0,0,0,0,1,0,0,0,0,1,0,0,0,0,1],"contentsRect":{"y":0,"x":0,"width":1,"height":1},"opacity":1,"edgeAntialiasingMask":251658240,"height":1080,"hidden":false,"anchorPoint":{"pointX":0.5,"pointY":0.5}},"objectID":"0","layers":[{"animations":[],"initialState":{"affineTransform":[1,0,0,1,0,0],"masksToBounds":false,"rotation":0,"scale":1,"position":{"pointX":960,"pointY":540},"width":1920,"sublayerTransform":[1,0,0,0,0,1,0,0,0,0,1,-0.00035007912466775983,0,0,0,1],"contentsRect":{"y":0,"x":0,"width":1,"height":1},"opacity":1,"edgeAntialiasingMask":251658240,"height":1080,"hidden":false,"anchorPoint":{"pointX":0.5,"pointY":0.5}},"layers":[{"animations":[{"repeatCount":0,"timingControlPoint2y":0.9959721565246582,"removedOnCompletion":false,"from":{"pointX":2880,"pointY":540},"timingFunction":"custom","additive":false,"timeOffset":0,"autoreverses":false,"timingControlPoint1x":0.49705871939659119,"fillMode":"both","property":"position","duration":0.75,"beginTime":0,"timingControlPoint2x":0.49811732769012451,"timingControlPoint1y":0,"to":{"pointX":960,"pointY":540}}],"layers":[],"texturedRectangle":{"isBackgroundTexture":false,"singleTextureOpacity":1,"textureType":0,"textBaseline":0,"textXHeight":0,"isVerticalText":false},"initialState":{"affineTransform":[1,0,0,1,0,0],"masksToBounds":false,"rotation":0,"scale":1,"position":{"pointX":960,"pointY":540},"width":1920,"sublayerTransform":[1,0,0,0,0,1,0,0,0,0,1,0,0,0,0,1],"contentsRect":{"y":0,"x":0,"width":1,"height":1},"opacity":1,"edgeAntialiasingMask":0,"height":1080,"hidden":false,"anchorPoint":{"pointX":0.5,"pointY":0.5}},"texture":"9076D6E0EFACFF14A26F2273D9135919"},{"animations":[{"repeatCount":0,"timingControlPoint2y":0.9959721565246582,"removedOnCompletion":false,"from":{"pointX":960,"pointY":540},"timingFunction":"custom","additive":false,"timeOffset":0,"autoreverses":false,"timingControlPoint1x":0.49705871939659119,"fillMode":"both","property":"position","duration":0.75,"beginTime":0,"timingControlPoint2x":0.49811732769012451,"timingControlPoint1y":0,"to":{"pointX":-960,"pointY":540}}],"layers":[],"texturedRectangle":{"isBackgroundTexture":false,"singleTextureOpacity":1,"textureType":0,"textBaseline":0,"textXHeight":0,"isVerticalText":false},"initialState":{"affineTransform":[1,0,0,1,0,0],"masksToBounds":false,"rotation":0,"scale":1,"position":{"pointX":960,"pointY":540},"width":1920,"sublayerTransform":[1,0,0,0,0,1,0,0,0,0,1,0,0,0,0,1],"contentsRect":{"y":0,"x":0,"width":1,"height":1},"opacity":1,"edgeAntialiasingMask":0,"height":1080,"hidden":false,"anchorPoint":{"pointX":0.5,"pointY":0.5}},"texture":"C22916240A8F8EF9D314E0ED6FA88D7B"}]}]},"effects":[],"duration":0.75,"type":"transition","attributes":{"direction":12},"name":"apple:push","objectID":"0"}],"automaticPlay":false,"hyperlinks":[],"accessibility":[{"text":"be391fa3-837d-4f33-9734-98a7212237f2_md.jpeg","targetRectangle":{"y":644.568410462776,"x":30.428571428571502,"width":1071.46875,"height":369.57013803773953}},{"text":"￼","targetRectangle":{"y":1044.1879879236221,"x":947.38800010796695,"width":25.224000000000046,"height":25.6240234375}},{"text":"BTV-logo.png","targetRectangle":{"y":902.76159536652688,"x":1658.8453806549846,"width":183.15625,"height":104.19441049535635}},{"text":"25thAnniversary Image Promo | BTV ","targetRectangle":{"y":113.49315881729126,"x":21.364135980606054,"width":17.476562500000053,"height":279.8046875}},{"text":"c164cb39-6eca-4928-8cae-5e12299b3cd2_md.jpeg","targetRectangle":{"y":37.198189134808842,"x":1141.7703572509267,"width":732.8453369140625,"height":494.67059326171858}},{"text":"Treatment by Drago Sholev | Positive Possum| ","targetRectangle":{"y":689.07812595367432,"x":1883.2617185115814,"width":17.4765625,"height":347.3984375}},{"text":"420fb45a-c6a0-438b-aa50-6f401d15b8af_md.jpeg","targetRectangle":{"y":37.113682092555329,"x":81.690140845070317,"width":1021.2307739257812,"height":573.48651123046875}}],"baseLayer":{"animations":[],"initialState":{"affineTransform":[1,0,0,1,0,0],"masksToBounds":false,"rotation":0,"scale":1,"position":{"pointX":960,"pointY":540},"width":1920,"sublayerTransform":[1,0,0,0,0,1,0,0,0,0,1,0,0,0,0,1],"contentsRect":{"y":0,"x":0,"width":1,"height":1},"opacity":1,"edgeAntialiasingMask":251658240,"height":1080,"hidden":false,"anchorPoint":{"pointX":0.5,"pointY":0.5}},"objectID":"0","layers":[{"animations":[],"initialState":{"affineTransform":[1,0,0,1,0,0],"masksToBounds":false,"rotation":0,"scale":1,"position":{"pointX":960,"pointY":540},"width":1920,"sublayerTransform":[1,0,0,0,0,1,0,0,0,0,1,-0.00035007912466775983,0,0,0,1],"contentsRect":{"y":0,"x":0,"width":1,"height":1},"opacity":1,"edgeAntialiasingMask":251658240,"height":1080,"hidden":false,"anchorPoint":{"pointX":0.5,"pointY":0.5}},"layers":[{"animations":[],"layers":[],"texturedRectangle":{"isBackgroundTexture":false,"singleTextureOpacity":1,"textureType":0,"textBaseline":0,"textXHeight":0,"isVerticalText":false},"initialState":{"affineTransform":[1,0,0,1,0,0],"masksToBounds":false,"rotation":0,"scale":1,"position":{"pointX":960,"pointY":540},"width":1920,"sublayerTransform":[1,0,0,0,0,1,0,0,0,0,1,0,0,0,0,1],"contentsRect":{"y":0,"x":0,"width":1,"height":1},"opacity":1,"edgeAntialiasingMask":0,"height":1080,"hidden":false,"anchorPoint":{"pointX":0.5,"pointY":0.5}},"texture":"C22916240A8F8EF9D314E0ED6FA88D7B"}]}]}}]}